[
  {
    "name": "maxNumericValue",
    "expected": 2500,
    "actual": 43170.60299999997,
    "values": [
      43170.60299999997
    ],
    "operator": "<=",
    "passed": false,
    "auditId": "largest-contentful-paint",
    "level": "warn",
    "url": "http://localhost:4100/fact-or-fiction",
    "auditTitle": "Largest Contentful Paint",
    "auditDocumentationLink": "https://developer.chrome.com/docs/lighthouse/performance/lighthouse-largest-contentful-paint/"
  },
  {
    "name": "maxNumericValue",
    "expected": 200,
    "actual": 5294.848499999982,
    "values": [
      5294.848499999982
    ],
    "operator": "<=",
    "passed": false,
    "auditId": "total-blocking-time",
    "level": "warn",
    "url": "http://localhost:4100/fact-or-fiction",
    "auditTitle": "Total Blocking Time",
    "auditDocumentationLink": "https://developer.chrome.com/docs/lighthouse/performance/lighthouse-total-blocking-time/"
  }
]